pyramid_autowire/__init__.py
pyramid_autowire/autowired_view.py
pyramid_autowire/decorator.py
pyramid_autowire/dependency_injection.py
pyramid_autowire/matchdict_injection.py
pyramid_autowire-1.0.2.dist-info/LICENSE
pyramid_autowire-1.0.2.dist-info/WHEEL
pyramid_autowire-1.0.2.dist-info/METADATA
pyramid_autowire-1.0.2.dist-info/RECORD
