Metadata-Version: 2.1
Name: pyramid-autowire
Version: 1.0.2
Summary: Dependency injection for pyramid views
Home-page: https://github.com/NickBeeuwsaert/pyramid_autowire
License: MIT
Author: Nick Beeuwsaert
Requires-Python: >=3.8,<4.0
Classifier: Development Status :: 5 - Production/Stable
Classifier: Framework :: Pyramid
Classifier: Intended Audience :: Developers
Classifier: License :: OSI Approved :: MIT License
Classifier: Programming Language :: Python :: 3
Classifier: Programming Language :: Python :: 3.8
Classifier: Programming Language :: Python :: 3.9
Requires-Dist: pyramid (>=1.5)
Requires-Dist: typing-extensions (>=3.7.4,<4.0.0)
Requires-Dist: zope.interface
